<game>
    <gameConditions>
        <statRequired name="életerő" min="1"/>
        <itemRequired name="kulcs" min="1"/>
        <!--Csak addig fut a játék, amíg legalább egy életerőd van és legalább egy db kulcs van nálad-->
        <!--Ha ez a feltétel nem teljesül, akkor: game over -->
    </gameConditions>

    <character>
        <stats>
            <stat name="Életerő" minValue="" maxValue="" value=""/>
            <stat name="Ügyesség" minValue="" maxValue="" value=""/>
            <stat name="Szerencse" minValue="" maxValue="" value=""/>
            <separator/>

            <stat name="Arany" minValue="" maxValue="" value=""/>
            <stat name="Drágakövek" minValue="" maxValue="" value=""/>

            <stat name="rejtett" minValue="" maxValue="" value="" hidden="true"/>
        </stats>
        <inventory title="Inventárium:">
            <item name="alma" amount="12"/>
            <item name="kulcs" amount="3"/>
            <item name="kard"/>
            <item name="rejtett" amount="2" hidden="true"/>
            <!-- Szükség esetén csoportorítható: <group name=""></group> címkék közé zárva, és akkor az inventorynak nem lesz címe-->
            <!-- A groupok is lehetnek (az összes elemükre vonatkozóan) hidden="true" -->
        </inventory>
    </character>

    <pages>
        <page id="init">
            <!--Kezdőoldal-->
        </page>

        <page id="1">
            <text>A Lorem Ipsum egy egyszerű szövegrészlete, szövegutánzata a betűszedő és nyomdaiparnak.</text>
            
            <options>
                <option>
                    <text>Első opció (Kapsz egy körtét és vesztesz egy életerőt, ha van nálad alma és szerencse)</text>
                    <execute>
                        <!--Conditions (ÉS kapcsolat van közöttük)-->
                        <itemRequired name="alma" min="2"/> <!-- equals / min, max-->
                        <itemRequired name="körte" min="2" group="gyümölcsök"/>
                        <statRequired name="szerencse" min="1"/> <!-- equals / min, max-->
                        
                        <dice stat="szerencse" type="2d6" relationSD="="/>  <!-- relation lehet: {=, !=, >, <, >=, <=} -->
                        <!-- Azért SD, hogy jelezze, milyen sorrendben értelmezendő a két szám.
                            Nem mindegy, hogy (Stat >= Dice) vagy (Dice >= Stat)
                        -->
                        
                        <!-- orField és andField (az execute eredendően andFieldként értelmezendő)-->

                        <!--To-do-->
                        <changeItem name="körte" amount="1"/> <!-- amount, decrease, increase -->
                        <changeStat name="Életerő" decrease="1"/> <!-- amount, decrease, increase -->
                        <changePage id="2"/>
                    </execute>
                    <execute>
                        <alert text="Nincs elég almád vagy szerencséd a folytatáshoz"/>
                        <!--Az alertek lényege: leokézhatod és ugyanott vagy, nem mozogsz sehova (csak egy javaslat)-->
                    </execute>
                </option>
                <option>
                    <text>Második opció</text>
                    <execute>
                        <changePage id="3"/>
                    </execute>
                    <!-- Rövidítési lehetőség: az execute mezők elhagyhatók, ha a parancs nincs feltételhez kötve-->
                </option>
            </options>
        </page>
    </pages>

</game>